crispy_forms_gds/__init__.py
crispy_forms_gds/apps.py
crispy_forms_gds/choices.py
crispy_forms_gds/fields.py
crispy_forms_gds/helper.py
crispy_forms_gds/models.py
crispy_forms_gds/utils.py
crispy_forms_gds/widgets.py
crispy_forms_gds/layout/__init__.py
crispy_forms_gds/layout/base.py
crispy_forms_gds/layout/buttons.py
crispy_forms_gds/layout/constants.py
crispy_forms_gds/layout/containers.py
crispy_forms_gds/layout/content.py
crispy_forms_gds/layout/fields.py
crispy_forms_gds/templates/gds/accordion-group.html
crispy_forms_gds/templates/gds/accordion.html
crispy_forms_gds/templates/gds/display_form.html
crispy_forms_gds/templates/gds/errors.html
crispy_forms_gds/templates/gds/errors_formset.html
crispy_forms_gds/templates/gds/field.html
crispy_forms_gds/templates/gds/inputs.html
crispy_forms_gds/templates/gds/uni_form.html
crispy_forms_gds/templates/gds/uni_formset.html
crispy_forms_gds/templates/gds/whole_uni_form.html
crispy_forms_gds/templates/gds/whole_uni_formset.html
crispy_forms_gds/templates/gds/layout/_conditional_radios.html
crispy_forms_gds/templates/gds/layout/baseinput.html
crispy_forms_gds/templates/gds/layout/breadcrumbs.html
crispy_forms_gds/templates/gds/layout/button.html
crispy_forms_gds/templates/gds/layout/checkboxes.html
crispy_forms_gds/templates/gds/layout/conditional_question.html
crispy_forms_gds/templates/gds/layout/conditional_radios.html
crispy_forms_gds/templates/gds/layout/div.html
crispy_forms_gds/templates/gds/layout/error_summary.html
crispy_forms_gds/templates/gds/layout/field_errors.html
crispy_forms_gds/templates/gds/layout/field_errors_block.html
crispy_forms_gds/templates/gds/layout/fieldset.html
crispy_forms_gds/templates/gds/layout/help_text.html
crispy_forms_gds/templates/gds/layout/help_text_and_errors.html
crispy_forms_gds/templates/gds/layout/multifield.html
crispy_forms_gds/templates/gds/layout/radio_item.html
crispy_forms_gds/templates/gds/layout/radios.html
crispy_forms_gds/templates/gds/layout/tab-link.html
crispy_forms_gds-2.0.1.dist-info/METADATA
crispy_forms_gds-2.0.1.dist-info/WHEEL
crispy_forms_gds-2.0.1.dist-info/top_level.txt
crispy_forms_gds-2.0.1.dist-info/RECORD
