Metadata-Version: 2.2
Name: crispy-forms-gds
Version: 2.0.1
Summary: Django application to add 'django-crispy-forms' layout objects for the GOV.UK Design System.
Author-email: Wildfish <developers@wildfish.com>
License: The MIT License (MIT)
Keywords: Django, django-crispy-forms, gov.uk, design system
Classifier: Development Status :: 5 - Production/Stable
Classifier: Framework :: Django
Classifier: Framework :: Django :: 5.0
Classifier: Framework :: Django :: 5.1
Classifier: Intended Audience :: Developers
Classifier: License :: OSI Approved :: BSD License
Classifier: Operating System :: OS Independent
Classifier: Programming Language :: Python
Classifier: Programming Language :: Python :: 3
Classifier: Programming Language :: Python :: 3.10
Classifier: Programming Language :: Python :: 3.11
Classifier: Programming Language :: Python :: 3.12
Classifier: Programming Language :: Python :: 3.13
Classifier: Topic :: Internet :: WWW/HTTP
Classifier: Topic :: Internet :: WWW/HTTP :: Dynamic Content
Classifier: Topic :: Software Development :: Libraries :: Python Modules
Requires-Python: >=3.10
Requires-Dist: django>=5.0
Requires-Dist: django-crispy-forms<2.4,>=2.0
